[1,["3fFLOUiktDVbpp1yaMGABf","f7WKU1xSxODq/fX1yqC6TM","d6yzP+hM9EIamdPfTgsiLZ","a9Sm9ZoB9BXIzFRPHqtNFh","62badXilJAk7+AMjFe/KCY","f1+/Em7alGH7isgBtqMBn6","8avN4ekTxGNJ+iOseuaWrf","4b7pVSDEVAOJcaW7Cgf3nG","a4QtG22vJGR5EwuDeu4FCk","90IUGtLjREyKD5Z+2UK1f3","c7PcMCGvxABZBO4aAc2zGM","2al3E4zOJPip9eJlg3Fg5M","e6QmWW14BACKKFTq4PQqkl","96sQXT6eFKB7EndbMtx/N0","711gITCC5DXqFAUai/BXGf","162cHQmyJNDassktWieLoW","46EuHBuy5BrLFZ1aJSbmI9","af7uEEPZ1E3b/99LrwGLVs","0dohUt5SBGhZnAWwhzk/4J","526VQBx/FA3YPo6dajAsng","caeT0UZ65BD5cc1anl03v2","65m7qB+W5C8J/PTWEcGgsC","6d0w2CuJlENK9NL/sa0VeZ","60JLfXwetOT7L3aWJN+YHi","27DmT9Vh9PGJEAWOiRf/sI","1fVRD5gpdITKTWNScOu3ME","75vcbKOIBF7qImdkL9sGNT","1dQ2yPj0hFXK5Rew417cOI","c6jawi+wZF5rb57rHbTP0t","70Z48/QCtMZoIsw3/FAfgv","9cIDGvMHNFoosZ329AW9C+","3dxzTwbpNNQa+SXTn+LRCt"],["_textureSetter","value"],["cc.SpriteFrame",["cc.AnimationClip",["_name","_duration","sample","curveData"],0,11]],[[1,0,1,2,3,4]],[[[{"name":"500170_attack_hit-play_11","rect":[12,23,165,158],"offset":[-1.5,-3],"originalSize":[192,198],"capInsets":[0,0,0,0]}],[0],0,[0],[0],[0]],[[{"name":"500170_attack_hit-play_08","rect":[0,0,192,198],"offset":[0,0],"originalSize":[192,198],"capInsets":[0,0,0,0]}],[0],0,[0],[0],[1]],[[{"name":"500170_attack_hit-play_04","rect":[0,0,192,198],"offset":[0,0],"originalSize":[192,198],"capInsets":[0,0,0,0]}],[0],0,[0],[0],[2]],[[{"name":"500170_attack_hit-play_09","rect":[9,26,165,155],"offset":[-4.5,-4.5],"originalSize":[192,198],"capInsets":[0,0,0,0]}],[0],0,[0],[0],[3]],[[{"name":"500170_attack_hit-play_00","rect":[3,24,176,174],"offset":[-5,-12],"originalSize":[192,198],"capInsets":[0,0,0,0]}],[0],0,[0],[0],[4]],[[{"name":"500170_attack_hit-play_12","rect":[12,20,167,159],"offset":[-0.5,-0.5],"originalSize":[192,198],"capInsets":[0,0,0,0]}],[0],0,[0],[0],[5]],[[{"name":"500170_attack_hit-play_14","rect":[12,16,170,164],"offset":[1,1],"originalSize":[192,198],"capInsets":[0,0,0,0]}],[0],0,[0],[0],[6]],[[[0,"arrow1Boom",0.5333333333333333,30,[{},"comps",11,[{},"cc.Sprite",11,[{},"spriteFrame",12,[[[{"frame":0},"value",6,0],[{"frame":0.03333333333333333},"value",6,1],[{"frame":0.06666666666666667},"value",6,2],[{"frame":0.1},"value",6,3],[{"frame":0.13333333333333333},"value",6,4],[{"frame":0.16666666666666666},"value",6,5],[{"frame":0.2},"value",6,6],[{"frame":0.23333333333333334},"value",6,7],[{"frame":0.26666666666666666},"value",6,8],[{"frame":0.3},"value",6,9],[{"frame":0.3333333333333333},"value",6,10],[{"frame":0.36666666666666664},"value",6,11],[{"frame":0.4},"value",6,12],[{"frame":0.43333333333333335},"value",6,13],[{"frame":0.4666666666666667},"value",6,14],[{"frame":0.5},"value",6,15]],11,11,11,11,11,11,11,11,11,11,11,11,11,11,11,11]]]]]],0,0,[0,0,0,0,0,0,0,0,0,0,0,0,0,0,0,0],[1,1,1,1,1,1,1,1,1,1,1,1,1,1,1,1],[7,8,9,10,11,12,13,14,15,16,17,18,19,20,21,22]],[[{"name":"500170_attack_hit-play_26","rect":[191,197,1,1],"offset":[95.5,-98.5],"originalSize":[192,198],"capInsets":[0,0,0,0]}],[0],0,[0],[0],[23]],[[{"name":"500170_attack_hit-play_07","rect":[0,0,192,198],"offset":[0,0],"originalSize":[192,198],"capInsets":[0,0,0,0]}],[0],0,[0],[0],[24]],[[{"name":"500170_attack_hit-play_02","rect":[0,0,192,198],"offset":[0,0],"originalSize":[192,198],"capInsets":[0,0,0,0]}],[0],0,[0],[0],[25]],[[{"name":"500170_attack_hit-play_06","rect":[0,0,192,198],"offset":[0,0],"originalSize":[192,198],"capInsets":[0,0,0,0]}],[0],0,[0],[0],[26]],[[{"name":"500170_attack_hit-play_01","rect":[0,0,192,198],"offset":[0,0],"originalSize":[192,198],"capInsets":[0,0,0,0]}],[0],0,[0],[0],[27]],[[{"name":"500170_attack_hit-play_10","rect":[12,23,165,158],"offset":[-1.5,-3],"originalSize":[192,198],"capInsets":[0,0,0,0]}],[0],0,[0],[0],[28]],[[{"name":"500170_attack_hit-play_03","rect":[0,0,192,198],"offset":[0,0],"originalSize":[192,198],"capInsets":[0,0,0,0]}],[0],0,[0],[0],[29]],[[{"name":"500170_attack_hit-play_13","rect":[12,16,170,164],"offset":[1,1],"originalSize":[192,198],"capInsets":[0,0,0,0]}],[0],0,[0],[0],[30]],[[{"name":"500170_attack_hit-play_05","rect":[0,0,192,198],"offset":[0,0],"originalSize":[192,198],"capInsets":[0,0,0,0]}],[0],0,[0],[0],[31]]]]